nrodataset/__init__.py
nrodataset/__version__.py
nrodataset/core.py
nrodataset/networks/ba_isd0_k4_100.mat
nrodataset/networks/ba_isd0_k4_500.mat
nrodataset/networks/eh_isd0_k4_100.mat
nrodataset/networks/eh_isd0_k4_500.mat
nrodataset/networks/er_isd0_k4_100.mat
nrodataset/networks/er_isd0_k4_500.mat
nrodataset/networks/er_isd0_k8_100.mat
nrodataset/networks/ml_isd0_k4_100.mat
nrodataset/networks/qs_isd0_k4_100.mat
nrodataset/networks/qs_isd0_k4_500.mat
nrodataset/networks/rh_isd0_k4_100.mat
nrodataset/networks/rt_isd0_k4_100.mat
nrodataset/networks/rt_isd0_k4_500.mat
nrodataset/networks/sf_isd0_k4_100.mat
nrodataset/networks/sf_isd0_k4_500.mat
nrodataset/networks/sf_isd0_k8_100.mat
nrodataset/networks/so_isd0_k4_100.mat
nrodataset/networks/so_isd0_k4_500.mat
nrodataset-0.2.1.dist-info/LICENSE
nrodataset-0.2.1.dist-info/METADATA
nrodataset-0.2.1.dist-info/WHEEL
nrodataset-0.2.1.dist-info/top_level.txt
nrodataset-0.2.1.dist-info/RECORD
