Metadata-Version: 2.1
Name: nrodataset
Version: 0.2.1
Summary: A dataset about network robustness optimization.
Home-page: https://github.com/chengpei-wu/NRODataset
Author: Chengpei Wu
Author-email: chengpei.wu@hotmail.com
License: MIT
Classifier: License :: OSI Approved :: MIT License
Classifier: Programming Language :: Python
Classifier: Programming Language :: Python :: 3
Classifier: Programming Language :: Python :: 3.6
Classifier: Programming Language :: Python :: Implementation :: CPython
Classifier: Programming Language :: Python :: Implementation :: PyPy
Requires-Python: >=3.6.0
License-File: LICENSE
Requires-Dist: scipy
Requires-Dist: networkx
